{
  "objectInfo" : {
    "id" : "4lD8s7If0dIjR6Zie2hoWX",
    "name" : "m_MYSQL_Snowflake_RejectRows",
    "type" : "DTEMPLATE",
    "metadata" : {
      "modelVersion" : {
        "major" : 0,
        "minor" : 0
      },
      "repoInfo" : {
        "repoHandle" : "010Q2I1700000000003X"
      },
      "contextAttributes" : [ {
        "name" : "id",
        "value" : "@1"
      } ],
      "additionalInfo" : {
        "description" : "",
        "contentType" : "JSON",
        "documentState" : "VALID"
      }
    }
  },
  "dataFileExtension" : "zip",
  "updateTime" : "2025-03-14T20:41:12.735Z",
  "objectRefs" : [ {
    "id" : "1RWKgtCbTuchAzrV3oTngR",
    "name" : "VS_SnowflakeV2",
    "type" : "Connection",
    "metadata" : {
      "modelVersion" : {
        "major" : 0,
        "minor" : 0
      },
      "repoInfo" : {
        "repoHandle" : "010Q2I0B00000000000X"
      },
      "contextAttributes" : null,
      "additionalInfo" : {
        "description" : null,
        "contentType" : "JSON",
        "documentState" : "COMPLETE"
      }
    },
    "path" : "/SYS"
  }, {
    "id" : "4YpRqLxa08GiXSdOMFlmAt",
    "name" : "VS_MYSQL",
    "type" : "Connection",
    "metadata" : {
      "modelVersion" : {
        "major" : 0,
        "minor" : 0
      },
      "repoInfo" : {
        "repoHandle" : "010Q2I0B000000000006"
      },
      "contextAttributes" : null,
      "additionalInfo" : {
        "description" : null,
        "contentType" : "JSON",
        "documentState" : "COMPLETE"
      }
    },
    "path" : "/SYS"
  } ],
  "readableFileExtension" : null,
  "readableFilePresent" : false
}